cskipdict/__init__.py
cskipdict/_skiplist.so
cskipdict-0.0.4.dist-info/DESCRIPTION.rst
cskipdict-0.0.4.dist-info/METADATA
cskipdict-0.0.4.dist-info/RECORD
cskipdict-0.0.4.dist-info/WHEEL
cskipdict-0.0.4.dist-info/metadata.json
cskipdict-0.0.4.dist-info/top_level.txt
