Metadata-Version: 2.0
Name: cskipdict
Version: 0.0.4
Summary: A fast CFFI-based SkipDict implementation.
Home-page: https://github.com/zacharyvoase/python-cskipdict
Author: Zachary Voase
Author-email: zack@meat.io
License: UNLICENSE
Platform: UNKNOWN
Requires-Dist: cffi (>=1.4.0)
